[
  {
    "name": "Zmechanizowana Jednostka Szybkiego Reagowania",
    "logo": "https://media.discordapp.net/attachments/1073714315674255553/1474097559986372770/logopoprawka_zjsrasdsasad.png?ex=69989bd5&is=69974a55&hm=58720e815ca3cbb6cc8c45a8c56e62e3888c4bffbdddfb5ec40a8287c2d9163d&=&format=webp&quality=lossless&width=337&height=526",
    "discord": "https://discord.gg/ENDAJHRGRY",
    "position": [54, 19.0122],
    "status": "approved",
    "verified": false
  },
  {
    "name": "JW 1182 GROT",
    "logo": "https://media.discordapp.net/attachments/1073714315674255553/1474084616712360017/pl.png?ex=69988fc7&is=69973e47&hm=d38566e1df9b833cbfa5f7daf4bcfecddbc940e5a9854f89a9c133db80a97b83&=&format=webp&quality=lossless&width=230&height=230",
    "discord": "https://discord.gg/przyklad2",
    "position": [50.0919, 21.4116],
    "status": "banned",
    "verified": false
  },
  {
    "name": "JW 2305 GROM",
    "logo": "https://media.discordapp.net/attachments/1073714315674255553/1474084616712360017/pl.png?ex=69988fc7&is=69973e47&hm=d38566e1df9b833cbfa5f7daf4bcfecddbc940e5a9854f89a9c133db80a97b83&=&format=webp&quality=lossless&width=230&height=230",
    "discord": "https://discord.gg/m9TueyhAn3",
    "position": [51.4, 20.3],
    "status": "banned",
    "verified": false
  },
  {
    "name": "Legion 404",
    "logo": "https://media.discordapp.net/attachments/1073714315674255553/1474084616712360017/pl.png?ex=69988fc7&is=69973e47&hm=d38566e1df9b833cbfa5f7daf4bcfecddbc940e5a9854f89a9c133db80a97b83&=&format=webp&quality=lossless&width=230&height=230",
    "discord": "https://discord.gg/d5xKuBKG4P",
    "position": [51.1100, 17.0200],
    "status": "banned",
    "verified": false
  },
  {
    "name": "Jednostka Wojskowa Komandosów",
    "logo": "https://media.discordapp.net/attachments/1073714315674255553/1474084616712360017/pl.png?ex=69988fc7&is=69973e47&hm=d38566e1df9b833cbfa5f7daf4bcfecddbc940e5a9854f89a9c133db80a97b83&=&format=webp&quality=lossless&width=230&height=230",
    "discord": "https://discord.gg/przyklad3",
    "position": [50.6760, 18.6840],
    "status": "banned",
    "verified": false
  },
  {
    "name": "1 Armia Mozowsza",
    "logo": "https://media.discordapp.net/attachments/1073714315674255553/1474084616712360017/pl.png?ex=69988fc7&is=69973e47&hm=d38566e1df9b833cbfa5f7daf4bcfecddbc940e5a9854f89a9c133db80a97b83&=&format=webp&quality=lossless&width=230&height=230",
    "discord": "https://discord.gg/przyklad3",
    "position": [52.2297, 21.0122],
    "status": "banned",
    "verified": false
  },
  {
    "name": "Placówka 104",
    "logo": "https://media.discordapp.net/attachments/1073714315674255553/1474084616712360017/pl.png?ex=69988fc7&is=69973e47&hm=d38566e1df9b833cbfa5f7daf4bcfecddbc940e5a9854f89a9c133db80a97b83&=&format=webp&quality=lossless&width=230&height=230",
    "discord": "https://discord.gg/przyklad3",
    "position": [49.4, 22.3],
    "status": "banned",
    "verified": false
  },
  {
    "name": "JW AGAT 3940",
    "logo": "https://media.discordapp.net/attachments/1073714315674255553/1474084616712360017/pl.png?ex=69988fc7&is=69973e47&hm=d38566e1df9b833cbfa5f7daf4bcfecddbc940e5a9854f89a9c133db80a97b83&=&format=webp&quality=lossless&width=230&height=230",
    "discord": "https://discord.gg/RyNCD9UtYq",
    "position": [51.4, 21.3],
    "status": "banned",
    "verified": false
  },
  {
    "name": "Platinium Five",
    "logo": "https://media.discordapp.net/attachments/1073714315674255553/1474118751497748542/RBRM5_-_Logo_of_PLATINUM_FIVE.webp?ex=6998af92&is=69975e12&hm=5713fd572ad9788d26e6ee2750dbf67fea9f3d801bc13806b664ebf255af9954&=&format=webp&width=135&height=135",
    "discord": "https://discord.com/invite/pl5",
    "position": [51.88, -176.64],
    "status": "approved",
    "verified": true
  }

]
